GTMAnalysisToolkit/__init__.py
GTMAnalysisToolkit/gtm.py
GTMAnalysisToolkit/k3nerror.py
GTMAnalysisToolkit-1.0.2.dist-info/LICENSE
GTMAnalysisToolkit-1.0.2.dist-info/METADATA
GTMAnalysisToolkit-1.0.2.dist-info/WHEEL
GTMAnalysisToolkit-1.0.2.dist-info/top_level.txt
GTMAnalysisToolkit-1.0.2.dist-info/RECORD
