Metadata-Version: 2.1
Name: GTMAnalysisToolkit
Version: 1.0.2
Summary: Generative Topographic Mapping and Analysis Toolkit
Author: Eng. Alberto Biscalchin
Author-email: <biscalchin.mau.se@gmail.com>
Keywords: generative topographic mapping,dimensionality reduction,data visualization,machine learning,high-dimensional data analysis
Classifier: Development Status :: 5 - Production/Stable
Classifier: Intended Audience :: Developers
Classifier: Intended Audience :: Science/Research
Classifier: Programming Language :: Python :: 3
Classifier: Operating System :: OS Independent
License-File: LICENSE
Requires-Dist: numpy
Requires-Dist: scipy
Requires-Dist: matplotlib
Requires-Dist: scikit-learn
